OmniLabs/OmniClient.py
OmniLabs/__init__.py
omnilabs-0.0.1.dist-info/METADATA
omnilabs-0.0.1.dist-info/WHEEL
omnilabs-0.0.1.dist-info/licenses/LICENSE
omnilabs-0.0.1.dist-info/RECORD
