Metadata-Version: 2.4
Name: omnilabs
Version: 0.0.1
Summary: A Python client for the OmniRouter API
Project-URL: Homepage, https://omnilabs-ai.github.io
Project-URL: Issues, https://github.com/omnilabs-ai
Author-email: Satya Shah <shahsatya25@gmail.com>
License-Expression: MIT
License-File: LICENSE
Classifier: Operating System :: OS Independent
Classifier: Programming Language :: Python :: 3.12
Requires-Python: >=3.12
Requires-Dist: requests>=2.25.0
